autoheader/__init__.py
autoheader/api.py
autoheader/app.py
autoheader/banner.py
autoheader/cli.py
autoheader/config.py
autoheader/constants.py
autoheader/core.py
autoheader/filesystem.py
autoheader/filters.py
autoheader/headerlogic.py
autoheader/hooks.py
autoheader/licenses.py
autoheader/lsp.py
autoheader/models.py
autoheader/planner.py
autoheader/precommit.py
autoheader/sarif.py
autoheader/ui.py
autoheader/walker.py
autoheader-10.0.1.dist-info/METADATA
autoheader-10.0.1.dist-info/WHEEL
autoheader-10.0.1.dist-info/entry_points.txt
autoheader-10.0.1.dist-info/top_level.txt
autoheader-10.0.1.dist-info/RECORD
