Metadata-Version: 2.4
Name: autoheader
Version: 10.0.1
Summary: Enterprise-grade file header tool that injects repo-relative path headers into Python files
Author-email: dhruv13x <dhruv13x@gmail.com>
License: MIT © dhruv13x
Project-URL: Homepage, https://github.com/dhruv13x/autoheader
Project-URL: Source, https://github.com/dhruv13x/autoheader
Project-URL: Issues, https://github.com/dhruv13x/autoheader/issues
Keywords: headers,cli,utilities,tooling,automation,python-files
Classifier: License :: OSI Approved :: MIT License
Classifier: Programming Language :: Python :: 3
Classifier: Programming Language :: Python :: 3 :: Only
Classifier: Programming Language :: Python :: 3.8
Classifier: Programming Language :: Python :: 3.9
Classifier: Programming Language :: Python :: 3.10
Classifier: Programming Language :: Python :: 3.11
Classifier: Programming Language :: Python :: 3.12
Classifier: Environment :: Console
Classifier: Topic :: Software Development :: Documentation
Requires-Python: >=3.8
Requires-Dist: tomli; python_version < "3.11"
Requires-Dist: rich>=13.0.0
Requires-Dist: rich-argparse>=1.0.0
Provides-Extra: lsp
Requires-Dist: pygls>=2.0.0; extra == "lsp"
Provides-Extra: dev
Requires-Dist: pytest>=8.0.0; extra == "dev"
Requires-Dist: pytest-cov>=5.0.0; extra == "dev"
Requires-Dist: pytest-timeout>=2.2.0; extra == "dev"
Requires-Dist: pytest-json-report>=1.5.0; extra == "dev"
Requires-Dist: pytest-asyncio>=0.23.0; extra == "dev"
Requires-Dist: pytest-mock>=3.10.0; extra == "dev"
Requires-Dist: pyfakefs>=5.0.0; extra == "dev"
Requires-Dist: ruff>=0.6.0; extra == "dev"
Requires-Dist: black>=24.3.0; extra == "dev"
Requires-Dist: mypy>=1.11.0; extra == "dev"
Requires-Dist: PyYAML>=6.0; extra == "dev"
Requires-Dist: types-PyYAML>=6.0; extra == "dev"
Provides-Extra: precommit
Requires-Dist: pyyaml>=6.0; extra == "precommit"
